{
  "author": "Oliver Castle",
  "license": "Apache License-2.0",
  "name": "ocastle-win_service",
  "operatingsystem_support": [
  	{
  		"operatingsystem":"Windows"
  	}
  ],
  "project_page": "https://github.com/ocastle/puppet-win_service",
  "source": "https://github.com/ocastle/puppet-win_service",
  "issues_url": "https://github.com/ocastle/puppet-win_service/issues",
  "requirements": [],
  "summary": "This module allows for the setup and configuration management of Windows Services.",
  "tags": ["windows", "service", "win32"],
  "dependencies": [],
  "version": "0.0.8"
}